pypdfcodebook/__init__.py
pypdfcodebook/pdfcb_00a_pypdfcodebooklogo_2025-12-17.png
pypdfcodebook/pdfcb_03b_pdffunctions.py
pypdfcodebook/pdfcb_03c_codebook.py
pypdfcodebook/simple.py
pypdfcodebook-0.5.2.dist-info/licenses/LICENSE
pypdfcodebook-0.5.2.dist-info/METADATA
pypdfcodebook-0.5.2.dist-info/WHEEL
pypdfcodebook-0.5.2.dist-info/top_level.txt
pypdfcodebook-0.5.2.dist-info/RECORD
